odoo/addons/report_qweb_field_option/README.rst
odoo/addons/report_qweb_field_option/__init__.py
odoo/addons/report_qweb_field_option/__manifest__.py
odoo/addons/report_qweb_field_option/i18n/it.po
odoo/addons/report_qweb_field_option/i18n/ja.po
odoo/addons/report_qweb_field_option/i18n/nl.po
odoo/addons/report_qweb_field_option/i18n/nl_NL.po
odoo/addons/report_qweb_field_option/i18n/report_qweb_field_option.pot
odoo/addons/report_qweb_field_option/models/__init__.py
odoo/addons/report_qweb_field_option/models/ir_qweb.py
odoo/addons/report_qweb_field_option/models/qweb_field_options.py
odoo/addons/report_qweb_field_option/readme/CONFIGURE.md
odoo/addons/report_qweb_field_option/readme/CONTRIBUTORS.md
odoo/addons/report_qweb_field_option/readme/DESCRIPTION.md
odoo/addons/report_qweb_field_option/readme/ROADMAP.md
odoo/addons/report_qweb_field_option/readme/USAGE.md
odoo/addons/report_qweb_field_option/security/ir.model.access.csv
odoo/addons/report_qweb_field_option/security/qweb_field_options_security.xml
odoo/addons/report_qweb_field_option/static/description/icon.png
odoo/addons/report_qweb_field_option/static/description/index.html
odoo/addons/report_qweb_field_option/tests/__init__.py
odoo/addons/report_qweb_field_option/tests/test_models.py
odoo/addons/report_qweb_field_option/tests/test_report_qweb_field_options.py
odoo/addons/report_qweb_field_option/views/qweb_field_options_views.xml
odoo_addon_report_qweb_field_option-18.0.1.0.1.1.dist-info/METADATA
odoo_addon_report_qweb_field_option-18.0.1.0.1.1.dist-info/WHEEL
odoo_addon_report_qweb_field_option-18.0.1.0.1.1.dist-info/top_level.txt
odoo_addon_report_qweb_field_option-18.0.1.0.1.1.dist-info/RECORD
